LICENSE.txt
setup.cfg
setup.py
pleaseGZ/Package.py
pleaseGZ/__init__.py
pleaseGZ.egg-info/PKG-INFO
pleaseGZ.egg-info/SOURCES.txt
pleaseGZ.egg-info/dependency_links.txt
pleaseGZ.egg-info/requires.txt
pleaseGZ.egg-info/top_level.txt
pleaseGZ/DATA/100008.jpg
pleaseGZ/DATA/100023.jpg
pleaseGZ/DATA/100053.jpg
pleaseGZ/DATA/100078.jpg
pleaseGZ/DATA/100090.jpg
pleaseGZ/DATA/100122.jpg
pleaseGZ/DATA/100123.jpg
pleaseGZ/DATA/100128.jpg
pleaseGZ/DATA/100134.jpg
pleaseGZ/DATA/100143.jpg
pleaseGZ/DATA/100150.jpg
pleaseGZ/DATA/100157.jpg
pleaseGZ/DATA/100204.jpg
pleaseGZ/DATA/100237.jpg
pleaseGZ/DATA/100259.jpg
pleaseGZ/DATA/100263.jpg
pleaseGZ/DATA/100288.jpg
pleaseGZ/DATA/100295.jpg
pleaseGZ/DATA/100322.jpg
pleaseGZ/DATA/100335.jpg
pleaseGZ/DATA/100380.jpg
pleaseGZ/DATA/100382.jpg
pleaseGZ/DATA/100383.jpg
pleaseGZ/DATA/100402.jpg
pleaseGZ/DATA/100428.jpg
pleaseGZ/DATA/100434.jpg
pleaseGZ/DATA/100444.jpg
pleaseGZ/DATA/100445.jpg
pleaseGZ/DATA/100458.jpg
pleaseGZ/DATA/100474.jpg
pleaseGZ/DATA/100479.jpg
pleaseGZ/DATA/100506.jpg
pleaseGZ/DATA/100513.jpg
pleaseGZ/DATA/100520.jpg
pleaseGZ/DATA/100541.jpg
pleaseGZ/DATA/100561.jpg
pleaseGZ/DATA/100571.jpg
pleaseGZ/DATA/100601.jpg
pleaseGZ/DATA/100623.jpg
pleaseGZ/DATA/100672.jpg
pleaseGZ/DATA/100673.jpg
pleaseGZ/DATA/100724.jpg
pleaseGZ/DATA/100727.jpg
pleaseGZ/DATA/100730.jpg
pleaseGZ/DATA/100740.jpg
pleaseGZ/DATA/100744.jpg
pleaseGZ/DATA/100765.jpg
pleaseGZ/DATA/100774.jpg
pleaseGZ/DATA/100801.jpg
pleaseGZ/DATA/100813.jpg
pleaseGZ/DATA/100821.jpg
pleaseGZ/DATA/100822.jpg
pleaseGZ/DATA/100836.jpg
pleaseGZ/DATA/100852.jpg
pleaseGZ/DATA/100859.jpg
pleaseGZ/DATA/100861.jpg
pleaseGZ/DATA/100867.jpg
pleaseGZ/DATA/100887.jpg
pleaseGZ/DATA/100894.jpg
pleaseGZ/DATA/100938.jpg
pleaseGZ/DATA/100951.jpg
pleaseGZ/DATA/100986.jpg
pleaseGZ/DATA/101007.jpg
pleaseGZ/DATA/101061.jpg
pleaseGZ/DATA/101074.jpg
pleaseGZ/DATA/101092.jpg
pleaseGZ/DATA/101127.jpg
pleaseGZ/DATA/101133.jpg
pleaseGZ/DATA/101135.jpg
pleaseGZ/DATA/101140.jpg
pleaseGZ/DATA/101151.jpg
pleaseGZ/DATA/101164.jpg
pleaseGZ/DATA/101166.jpg
pleaseGZ/DATA/101181.jpg
pleaseGZ/DATA/101232.jpg
pleaseGZ/DATA/101239.jpg
pleaseGZ/DATA/101244.jpg
